jbarchart/__init__.py
jbarchart/static/widget.css
jbarchart/static/widget.js
jbarchart-0.0.0.dist-info/METADATA
jbarchart-0.0.0.dist-info/WHEEL
jbarchart-0.0.0.dist-info/RECORD
