Metadata-Version: 2.3
Name: jbarchart
Version: 0.0.0
Requires-Dist: anywidget
Provides-Extra: dev
Requires-Dist: jupyterlab; extra == 'dev'
Requires-Dist: watchfiles; extra == 'dev'
